odoo/addons/hr_expense_excluded_tax/README.rst
odoo/addons/hr_expense_excluded_tax/__init__.py
odoo/addons/hr_expense_excluded_tax/__manifest__.py
odoo/addons/hr_expense_excluded_tax/i18n/hr_expense_excluded_tax.pot
odoo/addons/hr_expense_excluded_tax/i18n/it.po
odoo/addons/hr_expense_excluded_tax/models/__init__.py
odoo/addons/hr_expense_excluded_tax/models/hr_expense.py
odoo/addons/hr_expense_excluded_tax/readme/CONTRIBUTORS.rst
odoo/addons/hr_expense_excluded_tax/readme/DESCRIPTION.rst
odoo/addons/hr_expense_excluded_tax/static/description/icon.png
odoo/addons/hr_expense_excluded_tax/static/description/index.html
odoo/addons/hr_expense_excluded_tax/tests/__init__.py
odoo/addons/hr_expense_excluded_tax/tests/test_hr_expense_excluded_tax.py
odoo/addons/hr_expense_excluded_tax/views/hr_expense_views.xml
odoo_addon_hr_expense_excluded_tax-15.0.1.0.0.4.dist-info/METADATA
odoo_addon_hr_expense_excluded_tax-15.0.1.0.0.4.dist-info/WHEEL
odoo_addon_hr_expense_excluded_tax-15.0.1.0.0.4.dist-info/top_level.txt
odoo_addon_hr_expense_excluded_tax-15.0.1.0.0.4.dist-info/RECORD
